django_sugar/__init__.py
django_sugar/database/__init__.py
django_sugar/lang/__init__.py
django_sugar/lang/base64.py
django_sugar/lang/codec.py
django_sugar/lang/common.py
django_sugar/lang/enum_mixin.py
django_sugar/lang/io.py
django_sugar/lang/random.py
django_sugar/lang/reflection.py
django_sugar/lang/strtool.py
django_sugar/lang/typetest.py
django_sugar/lang/uuid.py
django_sugar/valueobject/__init__.py
django_sugar/valueobject/abstractfield.py
django_sugar/valueobject/color.py
django_sugar/valueobject/datedesc.py
django_sugar/valueobject/daterange.py
django_sugar/valueobject/intrange.py
django_sugar/valueobject/intrangecollection.py
django_sugar/valueobject/password.py
django_sugar/web/__init__.py
django_sugar/web/auth.py
django_sugar/web/file_storage.py
django_sugar/web/http.py
django_sugar/web/jwt_base.py
django_sugar/web/pwd_encoder.py
django_sugar/web/token.py
django_sugar/web/token_jwt.py
django_sugar-0.1.0.dist-info/LICENSE
django_sugar-0.1.0.dist-info/METADATA
django_sugar-0.1.0.dist-info/WHEEL
django_sugar-0.1.0.dist-info/top_level.txt
django_sugar-0.1.0.dist-info/RECORD
